pygments_nitecode/NiteCodeLexer.py
pygments_nitecode/__init__.py
pygments_nitecode-0.0.7.dist-info/METADATA
pygments_nitecode-0.0.7.dist-info/WHEEL
pygments_nitecode-0.0.7.dist-info/entry_points.txt
pygments_nitecode-0.0.7.dist-info/top_level.txt
pygments_nitecode-0.0.7.dist-info/zip-safe
pygments_nitecode-0.0.7.dist-info/RECORD
